README.md
setup.cfg
setup.py
eventbot/__init__.py
eventbot/app.py
eventbot/settings.py
eventbot/wsgi.py
eventbot.egg-info/PKG-INFO
eventbot.egg-info/SOURCES.txt
eventbot.egg-info/dependency_links.txt
eventbot.egg-info/not-zip-safe
eventbot.egg-info/requires.txt
eventbot.egg-info/top_level.txt
eventbot/models/__init__.py
eventbot/models/event.py
eventbot/models/user.py
eventbot/receiver/__init__.py
eventbot/receiver/eventbot.py
eventbot/routes/__init__.py
eventbot/routes/api.py
eventbot/scripts/__init__.py
eventbot/scripts/create_tables.py
eventbot/utils/__init__.py
eventbot/utils/settings.py