Metadata-Version: 1.0
Name: eventbot
Version: 1.0.0
Summary: An omnibot-based service to do organization of basic events in slack.
Home-page: https://github.com/lyft/eventbot
Author: Ryan Lane
Author-email: rlane@lyft.com
License: apache2
Platform: UNKNOWN
